ljk_test_mcp/__init__.py
ljk_test_mcp-0.1.0.dist-info/WHEEL
ljk_test_mcp-0.1.0.dist-info/entry_points.txt
ljk_test_mcp-0.1.0.dist-info/METADATA
ljk_test_mcp-0.1.0.dist-info/RECORD
